sevae/__init__.py
sevae/models/sevae.py
sevae-1.0.2.dist-info/METADATA
sevae-1.0.2.dist-info/WHEEL
sevae-1.0.2.dist-info/RECORD
